acie/acie.py
acie-1.2.dist-info/LICENSE
acie-1.2.dist-info/METADATA
acie-1.2.dist-info/WHEEL
acie-1.2.dist-info/entry_points.txt
acie-1.2.dist-info/top_level.txt
acie-1.2.dist-info/RECORD
